nonebot_plugin_blackjack/__init__.py
nonebot_plugin_blackjack/card.py
nonebot_plugin_blackjack/game.py
nonebot_plugin_blackjack/sign.py
nonebot_plugin_blackjack-0.0.5.dist-info/METADATA
nonebot_plugin_blackjack-0.0.5.dist-info/WHEEL
nonebot_plugin_blackjack-0.0.5.dist-info/top_level.txt
nonebot_plugin_blackjack-0.0.5.dist-info/RECORD
